nonebot_plugin_system_command/__init__.py
nonebot_plugin_system_command/config.py
nonebot_plugin_system_command-0.1.5.dist-info/LICENSE
nonebot_plugin_system_command-0.1.5.dist-info/METADATA
nonebot_plugin_system_command-0.1.5.dist-info/WHEEL
nonebot_plugin_system_command-0.1.5.dist-info/RECORD
