Metadata-Version: 2.1
Name: nonebot-plugin-system-command
Version: 0.1.5
Summary: Call the system command in NoneBot2
Home-page: https://github.com/tkgs0/nonebot-plugin-system-command
License: MIT
Keywords: nonebot,nonebot2,nonebot_plugin,system,shell,cmd,powershell
Author: 月ヶ瀬
Requires-Python: >=3.9,<4.0
Classifier: License :: OSI Approved :: MIT License
Classifier: Programming Language :: Python :: 3
Classifier: Programming Language :: Python :: 3.9
Classifier: Programming Language :: Python :: 3.10
Classifier: Programming Language :: Python :: 3.11
Classifier: Programming Language :: Python :: 3.12
Classifier: Programming Language :: Python :: 3.13
Requires-Dist: nonebot2 (>=2.3.1,<3.0.0)
Project-URL: Repository, https://github.com/tkgs0/nonebot-plugin-system-command
